fpu/__init__.py
fpu/errors.py
fpu/flist.py
fpu/fp.py
fpu/utils.py
fpu-0.2.51.dist-info/LICENSE
fpu-0.2.51.dist-info/METADATA
fpu-0.2.51.dist-info/WHEEL
fpu-0.2.51.dist-info/top_level.txt
fpu-0.2.51.dist-info/RECORD
