Metadata-Version: 2.1
Name: fpu
Version: 0.2.51
Summary: Functional Programming Utility
Home-page: https://github.com/johnklee/fpu
Author: johnklee
Author-email: puremonkey2007@gmail.com
License: MIT
Platform: UNKNOWN
Classifier: Programming Language :: Python :: 3
Classifier: Development Status :: 3 - Alpha
Classifier: Natural Language :: English
Classifier: Environment :: Web Environment
Classifier: Intended Audience :: Developers
Classifier: License :: OSI Approved :: MIT License
Classifier: Operating System :: OS Independent
Classifier: Topic :: Software Development :: Libraries :: Python Modules
